atek_main/__init__.py
atek_main/connect.py
atek_main/df_toolz.py
atek_main-0.1.5.dist-info/WHEEL
atek_main-0.1.5.dist-info/METADATA
atek_main-0.1.5.dist-info/RECORD
